dask_saturn/__init__.py
dask_saturn/_version.py
dask_saturn/backoff.py
dask_saturn/core.py
dask_saturn/external.py
dask_saturn/plugins.py
dask_saturn/settings.py
dask_saturn-0.4.4.dist-info/LICENSE
dask_saturn-0.4.4.dist-info/METADATA
dask_saturn-0.4.4.dist-info/WHEEL
dask_saturn-0.4.4.dist-info/top_level.txt
dask_saturn-0.4.4.dist-info/RECORD
