Metadata-Version: 2.1
Name: dask-saturn
Version: 0.4.4
Summary: Dask Cluster objects in Saturn Cloud
Home-page: https://saturncloud.io/
Maintainer: Saturn Cloud Developers
Maintainer-email: dev@saturncloud.io
License: BSD-3-Clause
Project-URL: Documentation, http://docs.saturncloud.io
Project-URL: Source, https://github.com/saturncloud/dask-saturn
Project-URL: Issue Tracker, https://github.com/saturncloud/dask-saturn/issues
Keywords: dask saturn cloud distributed cluster
Classifier: Development Status :: 4 - Beta
Classifier: License :: OSI Approved :: BSD License
Classifier: Intended Audience :: Developers
Classifier: Intended Audience :: Science/Research
Classifier: Topic :: Scientific/Engineering
Classifier: Topic :: System :: Distributed Computing
Classifier: Programming Language :: Python :: 3
Classifier: Programming Language :: Python :: 3.6
Classifier: Programming Language :: Python :: 3.7
License-File: LICENSE
Requires-Dist: distributed
Requires-Dist: packaging
Requires-Dist: requests
Requires-Dist: cryptography
